<Gesture Name="caret04" Subject="2" Speed="medium">
	<Point X="199" Y="206" T="1" />
	<Point X="201" Y="202" T="2" />
	<Point X="203" Y="197" T="3" />
	<Point X="206" Y="189" T="4" />
	<Point X="211" Y="176" T="5" />
	<Point X="214" Y="169" T="6" />
	<Point X="233" Y="137" T="7" />
	<Point X="237" Y="132" T="8" />
	<Point X="243" Y="127" T="9" />
	<Point X="246" Y="123" T="10" />
	<Point X="249" Y="120" T="11" />
	<Point X="251" Y="118" T="12" />
	<Point X="253" Y="115" T="13" />
	<Point X="255" Y="113" T="14" />
	<Point X="256" Y="111" T="15" />
	<Point X="257" Y="110" T="16" />
	<Point X="259" Y="107" T="17" />
	<Point X="260" Y="105" T="18" />
	<Point X="261" Y="102" T="19" />
	<Point X="262" Y="101" T="20" />
	<Point X="264" Y="99" T="21" />
	<Point X="265" Y="98" T="22" />
	<Point X="266" Y="97" T="23" />
	<Point X="266" Y="96" T="24" />
	<Point X="267" Y="97" T="25" />
	<Point X="268" Y="100" T="26" />
	<Point X="270" Y="104" T="27" />
	<Point X="272" Y="108" T="28" />
	<Point X="274" Y="113" T="29" />
	<Point X="276" Y="118" T="30" />
	<Point X="277" Y="124" T="31" />
	<Point X="278" Y="129" T="32" />
	<Point X="281" Y="139" T="33" />
	<Point X="283" Y="148" T="34" />
	<Point X="284" Y="153" T="35" />
	<Point X="286" Y="157" T="36" />
	<Point X="287" Y="162" T="37" />
	<Point X="288" Y="164" T="38" />
	<Point X="289" Y="166" T="39" />
	<Point X="290" Y="169" T="40" />
	<Point X="291" Y="173" T="41" />
	<Point X="292" Y="174" T="42" />
	<Point X="294" Y="178" T="43" />
	<Point X="295" Y="181" T="44" />
	<Point X="296" Y="184" T="45" />
	<Point X="298" Y="187" T="46" />
	<Point X="299" Y="190" T="47" />
	<Point X="299" Y="192" T="48" />
	<Point X="300" Y="193" T="49" />
	<Point X="301" Y="194" T="50" />
	<Point X="301" Y="195" T="51" />
	<Point X="301" Y="196" T="52" />
	<Point X="301" Y="197" T="53" />
	<Point X="301" Y="198" T="54" />
	<Point X="302" Y="198" T="55" />
	<Point X="302" Y="199" T="56" />
	<Point X="302" Y="200" T="57" />
	<Point X="303" Y="201" T="58" />
	<Point X="303" Y="202" T="59" />
	<Point X="304" Y="203" T="60" />
	<Point X="304" Y="204" T="61" />
	<Point X="304" Y="205" T="62" />
	<Point X="305" Y="206" T="63" />
	<Point X="305" Y="207" T="64" />
	<Point X="305" Y="208" T="65" />
	<Point X="305" Y="209" T="66" />
	<Point X="306" Y="210" T="67" />
</Gesture>