<Gesture Name="right-square-bracket10" Subject="1" Speed="medium">
	<Point X="253" Y="42" T="1" />
	<Point X="254" Y="43" T="2" />
	<Point X="254" Y="44" T="3" />
	<Point X="255" Y="44" T="4" />
	<Point X="256" Y="44" T="5" />
	<Point X="257" Y="44" T="6" />
	<Point X="259" Y="45" T="7" />
	<Point X="260" Y="45" T="8" />
	<Point X="262" Y="45" T="9" />
	<Point X="265" Y="45" T="10" />
	<Point X="267" Y="45" T="11" />
	<Point X="268" Y="45" T="12" />
	<Point X="269" Y="45" T="13" />
	<Point X="270" Y="45" T="14" />
	<Point X="271" Y="45" T="15" />
	<Point X="272" Y="45" T="16" />
	<Point X="273" Y="45" T="17" />
	<Point X="274" Y="45" T="18" />
	<Point X="274" Y="46" T="19" />
	<Point X="275" Y="49" T="20" />
	<Point X="275" Y="53" T="21" />
	<Point X="277" Y="57" T="22" />
	<Point X="277" Y="62" T="23" />
	<Point X="278" Y="69" T="24" />
	<Point X="278" Y="76" T="25" />
	<Point X="278" Y="85" T="26" />
	<Point X="278" Y="96" T="27" />
	<Point X="275" Y="107" T="28" />
	<Point X="273" Y="116" T="29" />
	<Point X="270" Y="125" T="30" />
	<Point X="268" Y="134" T="31" />
	<Point X="265" Y="142" T="32" />
	<Point X="263" Y="146" T="33" />
	<Point X="262" Y="151" T="34" />
	<Point X="261" Y="153" T="35" />
	<Point X="260" Y="156" T="36" />
	<Point X="259" Y="158" T="37" />
	<Point X="259" Y="159" T="38" />
	<Point X="258" Y="160" T="39" />
	<Point X="258" Y="162" T="40" />
	<Point X="258" Y="164" T="41" />
	<Point X="257" Y="165" T="42" />
	<Point X="257" Y="166" T="43" />
	<Point X="257" Y="167" T="44" />
	<Point X="257" Y="168" T="45" />
	<Point X="256" Y="168" T="46" />
	<Point X="256" Y="169" T="47" />
	<Point X="256" Y="170" T="48" />
	<Point X="255" Y="171" T="49" />
	<Point X="252" Y="171" T="50" />
	<Point X="248" Y="171" T="51" />
	<Point X="239" Y="171" T="52" />
	<Point X="227" Y="171" T="53" />
	<Point X="223" Y="171" T="54" />
	<Point X="219" Y="171" T="55" />
	<Point X="217" Y="171" T="56" />
	<Point X="216" Y="171" T="57" />
	<Point X="216" Y="170" T="58" />
</Gesture>